pysanejs/__init__.py
pysanejs/api.py
pysanejs/py.typed
pysanejs-2.0.5.dist-info/LICENSE
pysanejs-2.0.5.dist-info/METADATA
pysanejs-2.0.5.dist-info/WHEEL
pysanejs-2.0.5.dist-info/entry_points.txt
pysanejs-2.0.5.dist-info/RECORD
