Metadata-Version: 2.3
Name: pysanejs
Version: 2.0.5
Summary: Python client for SaneJS
License: AGPL-3.0-or-later
Author: Raphaël Vinot
Author-email: raphael@vinot.info
Requires-Python: >=3.9
Classifier: Environment :: Console
Classifier: Intended Audience :: Science/Research
Classifier: Intended Audience :: Telecommunications Industry
Classifier: License :: OSI Approved :: BSD License
Classifier: License :: OSI Approved :: GNU Affero General Public License v3 or later (AGPLv3+)
Classifier: Programming Language :: Python :: 3
Classifier: Programming Language :: Python :: 3.9
Classifier: Programming Language :: Python :: 3.10
Classifier: Programming Language :: Python :: 3.11
Classifier: Programming Language :: Python :: 3.12
Classifier: Programming Language :: Python :: 3.13
Classifier: Topic :: Internet
Classifier: Topic :: Security
Requires-Dist: requests (>=2.32.4)
Project-URL: Repository, https://github.com/Lookyloo/PySaneJS.git
